pyzomato/__init__.py
pyzomato/api.py
pyzomato/pyzomato.py
pyzomato-0.5.dist-info/DESCRIPTION.rst
pyzomato-0.5.dist-info/METADATA
pyzomato-0.5.dist-info/RECORD
pyzomato-0.5.dist-info/WHEEL
pyzomato-0.5.dist-info/metadata.json
pyzomato-0.5.dist-info/top_level.txt
