Metadata-Version: 2.0
Name: pyzomato
Version: 0.5
Summary: Python Zomato Api Wrapper
Home-page: https://github.com/fatihsucu/pyzomato
Author: Fatih Sucu
Author-email: fatihsucu0@gmail.com
License: MIT
Platform: UNKNOWN
